Mask2Former/__init__.py
Mask2Former/lighting_train_net.py
Mask2Former/predict.py
Mask2Former/train_net.py
Mask2Former/train_net_video.py
Mask2Former/demo/__init__.py
Mask2Former/demo/demo.py
Mask2Former/demo/predictor.py
Mask2Former/mask2former/__init__.py
Mask2Former/mask2former/config.py
Mask2Former/mask2former/maskformer_model.py
Mask2Former/mask2former/test_time_augmentation.py
Mask2Former/mask2former/data/__init__.py
Mask2Former/mask2former/data/dataset_mappers/__init__.py
Mask2Former/mask2former/data/dataset_mappers/coco_instance_new_baseline_dataset_mapper.py
Mask2Former/mask2former/data/dataset_mappers/coco_panoptic_new_baseline_dataset_mapper.py
Mask2Former/mask2former/data/dataset_mappers/mask_former_instance_dataset_mapper.py
Mask2Former/mask2former/data/dataset_mappers/mask_former_panoptic_dataset_mapper.py
Mask2Former/mask2former/data/dataset_mappers/mask_former_semantic_dataset_mapper.py
Mask2Former/mask2former/data/datasets/__init__.py
Mask2Former/mask2former/data/datasets/register_ade20k_full.py
Mask2Former/mask2former/data/datasets/register_ade20k_instance.py
Mask2Former/mask2former/data/datasets/register_ade20k_panoptic.py
Mask2Former/mask2former/data/datasets/register_coco_panoptic_annos_semseg.py
Mask2Former/mask2former/data/datasets/register_coco_stuff_10k.py
Mask2Former/mask2former/data/datasets/register_mapillary_vistas.py
Mask2Former/mask2former/data/datasets/register_mapillary_vistas_panoptic.py
Mask2Former/mask2former/evaluation/__init__.py
Mask2Former/mask2former/evaluation/instance_evaluation.py
Mask2Former/mask2former/modeling/__init__.py
Mask2Former/mask2former/modeling/criterion.py
Mask2Former/mask2former/modeling/matcher.py
Mask2Former/mask2former/modeling/backbone/__init__.py
Mask2Former/mask2former/modeling/backbone/swin.py
Mask2Former/mask2former/modeling/meta_arch/__init__.py
Mask2Former/mask2former/modeling/meta_arch/mask_former_head.py
Mask2Former/mask2former/modeling/meta_arch/per_pixel_baseline.py
mask2former-0.1.5.dist-info/METADATA
mask2former-0.1.5.dist-info/WHEEL
mask2former-0.1.5.dist-info/top_level.txt
mask2former-0.1.5.dist-info/RECORD
